Major Project Phase 1/rtl/data_memory.v
// ============================================================================
// Module: data_memory (Data RAM)
// File:   data_memory.v
//
// PURPOSE:
//   Read/write memory for LW and SW instructions.
//   - WRITE is synchronous (happens on clock edge when mem_write = 1)
//   - READ is combinational (instant output when mem_read = 1)
//   - 64 words = 256 bytes of data memory
//
// INPUTS:
//   clk        - Clock signal
//   mem_read   - 1 = output the data at the given address
//   mem_write  - 1 = write data to the given address
//   addr [31:0]     - Byte address (will be word-aligned: addr[31:2])
//   write_data [31:0] - Data to store (for SW)
//
// OUTPUTS:
//   read_data [31:0] - Data loaded from memory (for LW)
// ============================================================================

module data_memory (
    input  wire        clk,
    input  wire        mem_read,
    input  wire        mem_write,
    input  wire [31:0] addr,
    input  wire [31:0] write_data,
    output wire [31:0] read_data
);

    // 64 words of 32-bit memory
    reg [31:0] mem [0:63];

    // Initialize to 0 for simulation clarity
    integer i;
    initial begin
        for (i = 0; i < 64; i = i + 1)
            mem[i] = 32'd0;
    end

    // WRITE: synchronous — store on clock edge
    always @(posedge clk) begin
        if (mem_write) begin
            mem[addr[31:2]] <= write_data;
        end
    end

    // READ: combinational — output data immediately
    assign read_data = (mem_read) ? mem[addr[31:2]] : 32'd0;

endmodule

Major Project Phase 1/rtl/alu.v
// ============================================================================
// Module: alu (Arithmetic Logic Unit)
// File:   alu.v
//
// PURPOSE:
//   Performs arithmetic operations on two 32-bit inputs.
//   For this minimal CPU, only ADD and SUB are needed.
//
// INPUTS:
//   alu_in1    [31:0] - First operand  (from rs1)
//   alu_in2    [31:0] - Second operand (from rs2 or immediate)
//   alu_control [1:0] - Selects the operation:
//                        2'b00 = ADD
//                        2'b01 = SUB
//
// OUTPUTS:
//   alu_result [31:0] - Result of the operation
// ============================================================================

module alu (
    input  wire [31:0] alu_in1,
    input  wire [31:0] alu_in2,
    input  wire [1:0]  alu_control,
    output reg  [31:0] alu_result
);

    // ALU operation selection
    always @(*) begin
        case (alu_control)
            2'b00:   alu_result = alu_in1 + alu_in2;  // ADD
            2'b01:   alu_result = alu_in1 - alu_in2;  // SUB
            default: alu_result = alu_in1 + alu_in2;  // Default to ADD
        endcase
    end

endmodule

Major_Project_Phase_1/rtl/register_file.v
// ============================================================================
// Module: register_file
// File:   register_file.v
//
// PURPOSE:
//   The register file holds 32 general-purpose registers, each 32 bits wide.
//   - Two registers can be READ at the same time (combinational, no clock)
//   - One register can be WRITTEN on the rising clock edge
//   - Register x0 is ALWAYS zero (hardwired by RISC-V spec)
//
// INPUTS:
//   clk       - Clock signal
//   reg_write - Write enable (1 = write to rd)
//   rs1       [4:0]  - Address of first source register
//   rs2       [4:0]  - Address of second source register
//   rd        [4:0]  - Address of destination register
//   write_data[31:0] - Data to write into rd
//
// OUTPUTS:
//   read_data1 [31:0] - Value of register rs1
//   read_data2 [31:0] - Value of register rs2
// ============================================================================

module register_file (
    input  wire        clk,
    input  wire        reg_write,
    input  wire [4:0]  rs1,
    input  wire [4:0]  rs2,
    input  wire [4:0]  rd,
    input  wire [31:0] write_data,
    output wire [31:0] read_data1,
    output wire [31:0] read_data2
);

    // 32 registers, each 32 bits
    reg [31:0] registers [0:31];

    // Initialize all registers to 0 (for simulation clarity)
    integer i;
    initial begin
        for (i = 0; i < 32; i = i + 1)
            registers[i] = 32'd0;
    end

    // READ: combinational (instant, no clock)
    // x0 always reads as 0
    assign read_data1 = (rs1 == 5'd0) ? 32'd0 : registers[rs1];
    assign read_data2 = (rs2 == 5'd0) ? 32'd0 : registers[rs2];

    // WRITE: on rising clock edge, only if reg_write is enabled AND rd != x0
    always @(posedge clk) begin
        if (reg_write && rd != 5'd0) begin
            registers[rd] <= write_data;
        end
    end

endmodule

Major Project Phase 1/rtl/imm_gen.v
// ============================================================================
// Module: imm_gen (Immediate Generator)
// File:   imm_gen.v
//
// PURPOSE:
//   Extracts the immediate value from a 32-bit RISC-V instruction and
//   sign-extends it to 32 bits. Different instruction types place the
//   immediate bits in different positions:
//
//   I-type (ADDI, LW):  imm[11:0] = instruction[31:20]
//   S-type (SW):        imm[11:5] = instruction[31:25], imm[4:0] = instruction[11:7]
//
// INPUTS:
//   instruction [31:0] - The full 32-bit instruction
//
// OUTPUTS:
//   imm_out [31:0] - Sign-extended 32-bit immediate value
// ============================================================================

module imm_gen (
    input  wire [31:0] instruction,
    output reg  [31:0] imm_out
);

    wire [6:0] opcode;
    assign opcode = instruction[6:0];

    always @(*) begin
        case (opcode)
            // I-type: ADDI (0010011), LW (0000011)
            7'b0010011,
            7'b0000011: begin
                // imm[11:0] from instruction[31:20], sign-extended
                imm_out = {{20{instruction[31]}}, instruction[31:20]};
            end

            // S-type: SW (0100011)
            7'b0100011: begin
                // imm[11:5] from instruction[31:25], imm[4:0] from instruction[11:7]
                imm_out = {{20{instruction[31]}}, instruction[31:25], instruction[11:7]};
            end

            // R-type or unknown: no immediate needed
            default: begin
                imm_out = 32'd0;
            end
        endcase
    end

endmodule

Major Project Phase 1/Single cycle archive/rtl/control_unit.v
// ============================================================================
// Module: control_unit
// File:   control_unit.v
//
// PURPOSE:
//   Reads the opcode (and funct3/funct7 for R-type) from the instruction 
//   and generates all control signals that steer the datapath.
//
// INPUTS:
//   opcode  [6:0]  - instruction[6:0]   — identifies instruction type
//   funct3  [2:0]  - instruction[14:12] — sub-type (used for R-type)
//   funct7  [6:0]  - instruction[31:25] — distinguishes ADD from SUB
//
// OUTPUTS:
//   reg_write   - 1 = write result to register file
//   alu_src     - 0 = ALU input B is rs2; 1 = ALU input B is immediate
//   mem_read    - 1 = read from data memory (LW)
//   mem_write   - 1 = write to data memory (SW)
//   mem_to_reg  - 0 = register gets ALU result; 1 = register gets memory data
//   alu_control [1:0] - 00 = ADD, 01 = SUB
// ============================================================================

module control_unit (
    input  wire [6:0] opcode,
    input  wire [2:0] funct3,
    input  wire [6:0] funct7,
    output reg        reg_write,
    output reg        alu_src,
    output reg        mem_read,
    output reg        mem_write,
    output reg        mem_to_reg,
    output reg  [1:0] alu_control
);

    always @(*) begin
        // Default: everything off (safe defaults)
        reg_write   = 1'b0;
        alu_src     = 1'b0;
        mem_read    = 1'b0;
        mem_write   = 1'b0;
        mem_to_reg  = 1'b0;
        alu_control = 2'b00;

        case (opcode)
            // ---- R-type: ADD, SUB ----
            // opcode = 0110011
            7'b0110011: begin
                reg_write   = 1'b1;     // Write result to rd
                alu_src     = 1'b0;     // ALU input B = rs2
                mem_read    = 1'b0;     // No memory read
                mem_write   = 1'b0;     // No memory write
                mem_to_reg  = 1'b0;     // Write ALU result (not memory)

                // Distinguish ADD vs SUB using funct7
                if (funct7 == 7'b0100000)
                    alu_control = 2'b01; // SUB
                else
                    alu_control = 2'b00; // ADD
            end

            // ---- I-type: ADDI ----
            // opcode = 0010011
            7'b0010011: begin
                reg_write   = 1'b1;     // Write result to rd
                alu_src     = 1'b1;     // ALU input B = immediate
                mem_read    = 1'b0;     // No memory read
                mem_write   = 1'b0;     // No memory write
                mem_to_reg  = 1'b0;     // Write ALU result
                alu_control = 2'b00;    // ADD (rs1 + imm)
            end

            // ---- I-type: LW (Load Word) ----
            // opcode = 0000011
            7'b0000011: begin
                reg_write   = 1'b1;     // Write loaded data to rd
                alu_src     = 1'b1;     // ALU input B = immediate (offset)
                mem_read    = 1'b1;     // Read from data memory
                mem_write   = 1'b0;     // No memory write
                mem_to_reg  = 1'b1;     // Write memory data to register
                alu_control = 2'b00;    // ADD (rs1 + offset = address)
            end

            // ---- S-type: SW (Store Word) ----
            // opcode = 0100011
            7'b0100011: begin
                reg_write   = 1'b0;     // Do NOT write to register file
                alu_src     = 1'b1;     // ALU input B = immediate (offset)
                mem_read    = 1'b0;     // No memory read
                mem_write   = 1'b1;     // Write to data memory
                mem_to_reg  = 1'b0;     // Don't care (no reg write)
                alu_control = 2'b00;    // ADD (rs1 + offset = address)
            end

            // ---- Default: NOP-like behavior ----
            default: begin
                reg_write   = 1'b0;
                alu_src     = 1'b0;
                mem_read    = 1'b0;
                mem_write   = 1'b0;
                mem_to_reg  = 1'b0;
                alu_control = 2'b00;
            end
        endcase
    end

endmodule

Major Project Phase 1/rtl/instruction_memory.v
// ============================================================================
// Module: instruction_memory (Instruction ROM)
// File:   instruction_memory.v
//
// PURPOSE:
//   A read-only memory that stores the program. The PC gives an address,
//   and this module outputs the 32-bit instruction at that address.
//   Instructions are hardcoded for the demo program:
//     ADDI x1, x0, 5      =>  x1 = 0 + 5  = 5
//     ADDI x2, x0, 10     =>  x2 = 0 + 10 = 10
//     ADD  x3, x1, x2     =>  x3 = 5 + 10 = 15
//     SUB  x4, x3, x1     =>  x4 = 15 - 5 = 10
//     SW   x3, 0(x0)      =>  MEM[0] = x3 = 15
//     LW   x5, 0(x0)      =>  x5 = MEM[0] = 15
//
// INPUTS:
//   addr [31:0] - Byte address from the PC
//
// OUTPUTS:
//   instruction [31:0] - The 32-bit instruction at that address
// ============================================================================

module instruction_memory (
    input  wire [31:0] addr,
    output wire [31:0] instruction
);

    // Memory array: 64 words of 32 bits each (256 bytes, more than enough)
    reg [31:0] mem [0:63];

    // Hardcode the demo program
    // Machine code is derived from the RISC-V ISA encoding
    initial begin
        // ADDI x1, x0, 5     => imm=5, rs1=x0, funct3=000, rd=x1, opcode=0010011
        // Binary: 000000000101 | 00000 | 000 | 00001 | 0010011
        mem[0] = 32'h00500093;  // ADDI x1, x0, 5

        // ADDI x2, x0, 10    => imm=10, rs1=x0, funct3=000, rd=x2, opcode=0010011
        // Binary: 000000001010 | 00000 | 000 | 00010 | 0010011
        mem[1] = 32'h00A00113;  // ADDI x2, x0, 10

        // ADD x3, x1, x2     => funct7=0000000, rs2=x2, rs1=x1, funct3=000, rd=x3, opcode=0110011
        // Binary: 0000000 | 00010 | 00001 | 000 | 00011 | 0110011
        mem[2] = 32'h002081B3;  // ADD x3, x1, x2

        // SUB x4, x3, x1     => funct7=0100000, rs2=x1, rs1=x3, funct3=000, rd=x4, opcode=0110011
        // Binary: 0100000 | 00001 | 00011 | 000 | 00100 | 0110011
        mem[3] = 32'h40118233;  // SUB x4, x3, x1

        // SW x3, 0(x0)       => imm=0, rs2=x3, rs1=x0, funct3=010, opcode=0100011
        // Binary: 0000000 | 00011 | 00000 | 010 | 00000 | 0100011
        mem[4] = 32'h00302023;  // SW x3, 0(x0)

        // LW x5, 0(x0)       => imm=0, rs1=x0, funct3=010, rd=x5, opcode=0000011
        // Binary: 000000000000 | 00000 | 010 | 00101 | 0000011
        mem[5] = 32'h00002283;  // LW x5, 0(x0)

        // NOP (ADDI x0, x0, 0) — fills rest to avoid X values
        mem[6] = 32'h00000013;  // NOP
        mem[7] = 32'h00000013;  // NOP
    end

    // Read is combinational (no clock needed)
    // Divide byte address by 4 to get word index: addr[31:2]
    assign instruction = mem[addr[31:2]];

endmodule

Major Project Phase 1/rtl/pc.v
// ============================================================================
// Module: pc (Program Counter)
// File:   pc.v
// 
// PURPOSE:
//   Holds the address of the current instruction. On every rising clock edge,
//   it advances to the next instruction (PC + 4). On reset, it goes back to 0.
//
// INPUTS:
//   clk   - Clock signal
//   reset - Active-high synchronous reset
//
// OUTPUTS:
//   pc_out [31:0] - Current instruction address
// ============================================================================

module pc (
    input  wire        clk,
    input  wire        reset,
    output reg  [31:0] pc_out
);

    // On every clock edge: reset to 0, or advance by 4 (next word)
    always @(posedge clk) begin
        if (reset)
            pc_out <= 32'd0;        // Start from address 0
        else
            pc_out <= pc_out + 32'd4; // Move to next instruction (4 bytes each)
    end

endmodule

Major Project Phase 1/rtl/cpu_top.v
// ============================================================================
// Module: cpu_top (Top-Level CPU)
// File:   cpu_top.v
//
// PURPOSE:
//   Connects all sub-modules together to form the complete single-cycle
//   RV32I CPU. This is the "wiring diagram" — no logic here, just connections.
//
// INPUTS:
//   clk   - Clock signal
//   reset - Active-high synchronous reset
//
// The CPU has no external outputs in this simple version.
// In a real SoC, you would add I/O ports here.
// ============================================================================

module cpu_top (
    input wire clk,
    input wire reset
);

    // ========================================================================
    // Internal wires — these connect the modules together
    // ========================================================================

    // Program Counter
    wire [31:0] pc_current;

    // Instruction Memory
    wire [31:0] instruction;

    // Instruction fields (decoded from the instruction word)
    wire [6:0] opcode;
    wire [4:0] rd;
    wire [2:0] funct3;
    wire [4:0] rs1;
    wire [4:0] rs2;
    wire [6:0] funct7;

    // Control signals
    wire        reg_write;
    wire        alu_src;
    wire        mem_read;
    wire        mem_write;
    wire        mem_to_reg;
    wire [1:0]  alu_control;

    // Register file outputs
    wire [31:0] read_data1;  // rs1 value
    wire [31:0] read_data2;  // rs2 value

    // Immediate generator output
    wire [31:0] imm_value;

    // ALU
    wire [31:0] alu_input_b;  // Mux output: rs2 or immediate
    wire [31:0] alu_result;

    // Data memory
    wire [31:0] mem_read_data;

    // Write-back data (to register file)
    wire [31:0] write_back_data;

    // ========================================================================
    // Decode instruction fields
    // ========================================================================
    assign opcode = instruction[6:0];
    assign rd     = instruction[11:7];
    assign funct3 = instruction[14:12];
    assign rs1    = instruction[19:15];
    assign rs2    = instruction[24:20];
    assign funct7 = instruction[31:25];

    // ========================================================================
    // MUX: ALU input B selection
    //   alu_src = 0 → use rs2 (R-type: ADD, SUB)
    //   alu_src = 1 → use immediate (I-type: ADDI, LW; S-type: SW)
    // ========================================================================
    assign alu_input_b = (alu_src) ? imm_value : read_data2;

    // ========================================================================
    // MUX: Write-back data selection
    //   mem_to_reg = 0 → write ALU result to register (ADD, SUB, ADDI)
    //   mem_to_reg = 1 → write memory data to register (LW)
    // ========================================================================
    assign write_back_data = (mem_to_reg) ? mem_read_data : alu_result;

    // ========================================================================
    // Module Instantiations
    // ========================================================================

    // 1. Program Counter
    pc u_pc (
        .clk    (clk),
        .reset  (reset),
        .pc_out (pc_current)
    );

    // 2. Instruction Memory
    instruction_memory u_imem (
        .addr        (pc_current),
        .instruction (instruction)
    );

    // 3. Control Unit
    control_unit u_control (
        .opcode      (opcode),
        .funct3      (funct3),
        .funct7      (funct7),
        .reg_write   (reg_write),
        .alu_src     (alu_src),
        .mem_read    (mem_read),
        .mem_write   (mem_write),
        .mem_to_reg  (mem_to_reg),
        .alu_control (alu_control)
    );

    // 4. Immediate Generator
    imm_gen u_imm_gen (
        .instruction (instruction),
        .imm_out     (imm_value)
    );

    // 5. Register File
    register_file u_regfile (
        .clk        (clk),
        .reg_write  (reg_write),
        .rs1        (rs1),
        .rs2        (rs2),
        .rd         (rd),
        .write_data (write_back_data),
        .read_data1 (read_data1),
        .read_data2 (read_data2)
    );

    // 6. ALU
    alu u_alu (
        .alu_in1     (read_data1),
        .alu_in2     (alu_input_b),
        .alu_control (alu_control),
        .alu_result  (alu_result)
    );

    // 7. Data Memory
    data_memory u_dmem (
        .clk        (clk),
        .mem_read   (mem_read),
        .mem_write  (mem_write),
        .addr       (alu_result),
        .write_data (read_data2),
        .read_data  (mem_read_data)
    );

endmodule

Major Project Phase 1/Single cycle archive/sim/cpu_tb.v
// ============================================================================
// Testbench: cpu_tb
// File:      cpu_tb.v
//
// PURPOSE:
//   Simulates the single-cycle RV32I CPU.
//   - Generates a clock
//   - Applies reset for the first cycle
//   - Runs the demo program for several cycles
//   - Prints register values to verify correctness
//
// EXPECTED OUTPUT:
//   After the program runs:
//     x1 = 5   (ADDI x1, x0, 5)
//     x2 = 10  (ADDI x2, x0, 10)
//     x3 = 15  (ADD  x3, x1, x2)
//     x4 = 10  (SUB  x4, x3, x1)
//     x5 = 15  (LW   x5, 0(x0)  — loaded from memory after SW)
// ============================================================================

`timescale 1ns / 1ps

module cpu_tb;

    // ---- Clock and Reset ----
    reg clk;
    reg reset;

    // ---- Instantiate the CPU ----
    cpu_top uut (
        .clk   (clk),
        .reset (reset)
    );

    // ---- Clock Generation: 10ns period (100 MHz) ----
    initial begin
        clk = 0;
    end
    always #5 clk = ~clk;  // Toggle every 5ns → 10ns period

    // ---- Simulation ----
    initial begin
        // Optional: dump waveforms for GTKWave viewing
        $dumpfile("cpu_waves.vcd");
        $dumpvars(0, cpu_tb);

        // Apply reset
        reset = 1;
        #10;            // Hold reset for 1 clock cycle
        reset = 0;

        // Let the CPU run for 10 clock cycles (enough for 6 instructions + extra)
        #100;

        // ---- Print Results ----
        $display("============================================");
        $display("  Single-Cycle RV32I CPU — Simulation Results");
        $display("============================================");
        $display("  PC = %0d", uut.u_pc.pc_out);
        $display("");
        $display("  Register File:");
        $display("    x0  = %0d (hardwired zero)", uut.u_regfile.registers[0]);
        $display("    x1  = %0d (expected: 5)",    uut.u_regfile.registers[1]);
        $display("    x2  = %0d (expected: 10)",   uut.u_regfile.registers[2]);
        $display("    x3  = %0d (expected: 15)",   uut.u_regfile.registers[3]);
        $display("    x4  = %0d (expected: 10)",   uut.u_regfile.registers[4]);
        $display("    x5  = %0d (expected: 15)",   uut.u_regfile.registers[5]);
        $display("");
        $display("  Data Memory[0] = %0d (expected: 15)", uut.u_dmem.mem[0]);
        $display("============================================");

        // ---- Verify correctness ----
        if (uut.u_regfile.registers[1] == 32'd5 &&
            uut.u_regfile.registers[2] == 32'd10 &&
            uut.u_regfile.registers[3] == 32'd15 &&
            uut.u_regfile.registers[4] == 32'd10 &&
            uut.u_regfile.registers[5] == 32'd15 &&
            uut.u_dmem.mem[0] == 32'd15) begin
            $display("  >>> ALL TESTS PASSED! <<<");
        end else begin
            $display("  >>> SOME TESTS FAILED — check values above <<<");
        end

        $display("============================================");
        $finish;
    end

    // ---- Cycle-by-cycle trace (optional, helps debugging) ----
    always @(posedge clk) begin
        if (!reset) begin
            $display("[Cycle] PC=%0d  Instr=%h  ALU_result=%0d  RegWrite=%b  MemWrite=%b",
                     uut.u_pc.pc_out,
                     uut.u_imem.instruction,
                     uut.u_alu.alu_result,
                     uut.u_control.reg_write,
                     uut.u_control.mem_write);
        end
    end

endmodule

Major Project Phase 1/Single cycle archive/sim/cpu_waves.vcd
$date
	Mon Mar 30 21:03:11 2026
$end
$version
	Icarus Verilog
$end
$timescale
	1ps
$end
$scope module cpu_tb $end
$var reg 1 ! clk $end
$var reg 1 " reset $end
$scope module uut $end
$var wire 1 ! clk $end
$var wire 1 " reset $end
$var wire 32 # write_back_data [31:0] $end
$var wire 5 $ rs2 [4:0] $end
$var wire 5 % rs1 [4:0] $end
$var wire 1 & reg_write $end
$var wire 32 ' read_data2 [31:0] $end
$var wire 32 ( read_data1 [31:0] $end
$var wire 5 ) rd [4:0] $end
$var wire 32 * pc_current [31:0] $end
$var wire 7 + opcode [6:0] $end
$var wire 1 , mem_write $end
$var wire 1 - mem_to_reg $end
$var wire 32 . mem_read_data [31:0] $end
$var wire 1 / mem_read $end
$var wire 32 0 instruction [31:0] $end
$var wire 32 1 imm_value [31:0] $end
$var wire 7 2 funct7 [6:0] $end
$var wire 3 3 funct3 [2:0] $end
$var wire 1 4 alu_src $end
$var wire 32 5 alu_result [31:0] $end
$var wire 32 6 alu_input_b [31:0] $end
$var wire 2 7 alu_control [1:0] $end
$scope module u_alu $end
$var wire 32 8 alu_in2 [31:0] $end
$var wire 32 9 alu_in1 [31:0] $end
$var wire 2 : alu_control [1:0] $end
$var reg 32 ; alu_result [31:0] $end
$upscope $end
$scope module u_control $end
$var wire 3 < funct3 [2:0] $end
$var wire 7 = funct7 [6:0] $end
$var wire 7 > opcode [6:0] $end
$var reg 2 ? alu_control [1:0] $end
$var reg 1 4 alu_src $end
$var reg 1 / mem_read $end
$var reg 1 - mem_to_reg $end
$var reg 1 , mem_write $end
$var reg 1 & reg_write $end
$upscope $end
$scope module u_dmem $end
$var wire 32 @ addr [31:0] $end
$var wire 1 ! clk $end
$var wire 1 / mem_read $end
$var wire 1 , mem_write $end
$var wire 32 A write_data [31:0] $end
$var wire 32 B read_data [31:0] $end
$var integer 32 C i [31:0] $end
$upscope $end
$scope module u_imem $end
$var wire 32 D instruction [31:0] $end
$var wire 32 E addr [31:0] $end
$upscope $end
$scope module u_imm_gen $end
$var wire 32 F instruction [31:0] $end
$var wire 7 G opcode [6:0] $end
$var reg 32 H imm_out [31:0] $end
$upscope $end
$scope module u_pc $end
$var wire 1 ! clk $end
$var wire 1 " reset $end
$var reg 32 I pc_out [31:0] $end
$upscope $end
$scope module u_regfile $end
$var wire 1 ! clk $end
$var wire 5 J rd [4:0] $end
$var wire 1 & reg_write $end
$var wire 5 K rs1 [4:0] $end
$var wire 5 L rs2 [4:0] $end
$var wire 32 M write_data [31:0] $end
$var wire 32 N read_data2 [31:0] $end
$var wire 32 O read_data1 [31:0] $end
$var integer 32 P i [31:0] $end
$upscope $end
$upscope $end
$upscope $end
$enddefinitions $end
$comment Show the parameter values. $end
$dumpall
$end
#0
$dumpvars
b100000 P
bx O
bx N
bx M
bx L
bx K
bx J
bx I
bx H
bx G
bx F
bx E
bx D
b1000000 C
bx B
bx A
bx @
bx ?
bx >
bx =
bx <
bx ;
bx :
bx 9
bx 8
bx 7
bx 6
bx 5
x4
bx 3
bx 2
bx 1
bx 0
x/
bx .
x-
x,
bx +
bx *
bx )
bx (
bx '
x&
bx %
bx $
bx #
1"
0!
$end
#5000
b101 #
b101 M
b101 5
b101 ;
b101 @
b0 .
b0 B
b101 6
b101 8
b0 '
b0 A
b0 N
b0 (
b0 9
b0 O
b0 7
b0 :
b0 ?
0-
0,
0/
14
1&
b101 1
b101 H
b10011 G
b0 2
b0 =
b101 $
b101 L
b0 %
b0 K
b0 3
b0 <
b1 )
b1 J
b10011 +
b10011 >
b10100000000000010010011 0
b10100000000000010010011 D
b10100000000000010010011 F
b0 *
b0 E
b0 I
1!
#10000
0!
0"
#15000
b1010 #
b1010 M
b1010 5
b1010 ;
b1010 @
b1010 6
b1010 8
b1010 1
b1010 H
b1010 $
b1010 L
b10 )
b10 J
b101000000000000100010011 0
b101000000000000100010011 D
b101000000000000100010011 F
b100 *
b100 E
b100 I
1!
#20000
0!
#25000
b1111 #
b1111 M
b1111 5
b1111 ;
b1111 @
b1010 '
b1010 A
b1010 N
b101 (
b101 9
b101 O
04
1&
b0 1
b0 H
b110011 G
b10 $
b10 L
b1 %
b1 K
b11 )
b11 J
b110011 +
b110011 >
b1000001000000110110011 0
b1000001000000110110011 D
b1000001000000110110011 F
b1000 *
b1000 E
b1000 I
1!
#30000
0!
#35000
b1010 #
b1010 M
b101 6
b101 8
b1010 5
b1010 ;
b1010 @
b1 7
b1 :
b1 ?
1&
b101 '
b101 A
b101 N
b1111 (
b1111 9
b1111 O
b100000 2
b100000 =
b1 $
b1 L
b11 %
b11 K
b100 )
b100 J
b1000000000100011000001000110011 0
b1000000000100011000001000110011 D
b1000000000100011000001000110011 F
b1100 *
b1100 E
b1100 I
1!
#40000
0!
#45000
b0 #
b0 M
b0 6
b0 8
b0 5
b0 ;
b0 @
b1111 '
b1111 A
b1111 N
b0 (
b0 9
b0 O
1,
14
b0 7
b0 :
b0 ?
0&
b100011 G
b0 2
b0 =
b11 $
b11 L
b0 %
b0 K
b10 3
b10 <
b0 )
b0 J
b100011 +
b100011 >
b1100000010000000100011 0
b1100000010000000100011 D
b1100000010000000100011 F
b10000 *
b10000 E
b10000 I
1!
#50000
0!
#55000
b1111 #
b1111 M
b1111 .
b1111 B
b0 '
b0 A
b0 N
1-
1/
1&
0,
14
b11 G
b0 $
b0 L
b101 )
b101 J
b11 +
b11 >
b10001010000011 0
b10001010000011 D
b10001010000011 F
b10100 *
b10100 E
b10100 I
1!
#60000
0!
#65000
b0 #
b0 M
b0 .
b0 B
0-
0/
14
1&
b10011 G
b0 3
b0 <
b0 )
b0 J
b10011 +
b10011 >
b10011 0
b10011 D
b10011 F
b11000 *
b11000 E
b11000 I
1!
#70000
0!
#75000
b11100 *
b11100 E
b11100 I
1!
#80000
0!
#85000
bx #
bx M
bx 5
bx ;
bx @
bx 6
bx 8
bx '
bx A
bx N
bx (
bx 9
bx O
04
0&
bx G
bx 2
bx =
bx $
bx L
bx %
bx K
bx 3
bx <
bx )
bx J
bx +
bx >
bx 0
bx D
bx F
b100000 *
b100000 E
b100000 I
1!
#90000
0!
#95000
b100100 *
b100100 E
b100100 I
1!
#100000
0!
#105000
b101000 *
b101000 E
b101000 I
1!
